mcsm_benchs/Benchmark.py
mcsm_benchs/MatlabInterface.py
mcsm_benchs/OctaveInterface.py
mcsm_benchs/ResultsInterpreter.py
mcsm_benchs/SignalBank.py
mcsm_benchs/__init__.py
mcsm_benchs/benchmark_utils.py
mcsm_benchs-0.1.3.dist-info/LICENSE
mcsm_benchs-0.1.3.dist-info/METADATA
mcsm_benchs-0.1.3.dist-info/WHEEL
mcsm_benchs-0.1.3.dist-info/RECORD
