Metadata-Version: 2.3
Name: mcsm-benchs
Version: 0.1.3
Summary: mcsm-benchs: A benchmarking toolbox for Multi-Component Signal Methods.
Author: jmiramont
Author-email: jmiramontt@univ-lille.fr
Requires-Python: >=3.10
Classifier: Programming Language :: Python :: 3
Classifier: Programming Language :: Python :: 3.10
Classifier: Programming Language :: Python :: 3.11
Classifier: Programming Language :: Python :: 3.12
Classifier: Programming Language :: Python :: 3.13
Requires-Dist: matplotlib (>=3.5.1,<4.0.0)
Requires-Dist: numpy (>=2.1.0,<3.0.0)
Requires-Dist: pandas (>=2.2.3,<3.0.0)
Requires-Dist: plotly (>=5.10.0,<6.0.0)
Requires-Dist: pytest (>=7.0.1,<8.0.0)
Requires-Dist: pytest-cov (>=5.0.0,<6.0.0)
Requires-Dist: scipy (>=1.7.3,<2.0.0)
Requires-Dist: seaborn (>=0.12.0)
Requires-Dist: tqdm (>=4.66.4,<5.0.0)
Project-URL: Homepage, https://jmiramont.github.io/mcsm-benchs/
Project-URL: Repository, https://github.com/jmiramont/mcsm-benchs
